ai_rulez/__init__.py
ai_rulez/cli.py
ai_rulez/downloader.py
ai_rulez-3.6.1.dist-info/METADATA
ai_rulez-3.6.1.dist-info/WHEEL
ai_rulez-3.6.1.dist-info/entry_points.txt
ai_rulez-3.6.1.dist-info/top_level.txt
ai_rulez-3.6.1.dist-info/RECORD
