Metadata-Version: 2.4
Name: ai-rulez
Version: 3.6.1
Summary: ⚡ One config to rule them all. Centralized AI assistant configuration management - generate rules for Claude, Cursor, Copilot, Windsurf and more from a single YAML file.
Home-page: https://github.com/Goldziher/ai-rulez
Author: Na'aman Hirschfeld
Author-email: nhirschfeld@gmail.com
Project-URL: Homepage, https://goldziher.github.io/ai-rulez/
Project-URL: Documentation, https://goldziher.github.io/ai-rulez/
Project-URL: Bug Reports, https://github.com/Goldziher/ai-rulez/issues
Project-URL: Source, https://github.com/Goldziher/ai-rulez
Project-URL: Changelog, https://github.com/Goldziher/ai-rulez/releases
Project-URL: Funding, https://github.com/sponsors/Goldziher
Keywords: ai,ai-assistant,ai-rules,claude,cursor,copilot,windsurf,gemini,cline,continue-dev,mcp,model-context-protocol,cli,configuration,config,rules,generator,golang,go,development,developer-tools,automation,workflow,productivity,pre-commit,git-hooks,code-generation,ai-development,assistant-configuration,monorepo,presets,agents
Classifier: Development Status :: 4 - Beta
Classifier: Intended Audience :: Developers
Classifier: Topic :: Software Development :: Code Generators
Classifier: Topic :: Software Development :: Libraries :: Python Modules
Classifier: Topic :: Software Development :: Quality Assurance
Classifier: Topic :: Software Development :: Pre-processors
Classifier: Topic :: Text Processing :: General
Classifier: Topic :: Utilities
Classifier: License :: OSI Approved :: MIT License
Classifier: Programming Language :: Python :: 3
Classifier: Programming Language :: Python :: 3.8
Classifier: Programming Language :: Python :: 3.9
Classifier: Programming Language :: Python :: 3.10
Classifier: Programming Language :: Python :: 3.11
Classifier: Programming Language :: Python :: 3.12
Classifier: Programming Language :: Python :: 3.13
Classifier: Programming Language :: Python :: 3.14
Classifier: Programming Language :: Go
Classifier: Operating System :: OS Independent
Classifier: Operating System :: MacOS
Classifier: Operating System :: Microsoft :: Windows
Classifier: Operating System :: POSIX :: Linux
Classifier: Environment :: Console
Classifier: Environment :: Web Environment
Requires-Python: >=3.8
Dynamic: author
Dynamic: author-email
Dynamic: classifier
Dynamic: description
Dynamic: description-content-type
Dynamic: home-page
Dynamic: keywords
Dynamic: project-url
Dynamic: requires-python
Dynamic: summary
